odoo8_addon_l10n_ar_cash_register-8.0.1.0.0-py2.7-nspkg.pth
odoo_addons/l10n_ar_cash_register/__openerp__.py
odoo_addons/l10n_ar_cash_register/payment_mode_receipt_view.xml
odoo_addons/l10n_ar_cash_register/payment_mode_receipt.py
odoo_addons/l10n_ar_cash_register/account_voucher.py
odoo_addons/l10n_ar_cash_register/__init__.py
odoo_addons/l10n_ar_cash_register/cash_statement_view.xml
odoo_addons/l10n_ar_cash_register/cash_statement.py
odoo_addons/l10n_ar_cash_register/i18n/es_AR.po
odoo_addons/l10n_ar_cash_register/i18n/es_AR.mo
odoo_addons/l10n_ar_cash_register/wizard/pos_box.py
odoo_addons/l10n_ar_cash_register/wizard/__init__.py
odoo_addons/l10n_ar_cash_register/wizard/pos_box.xml
odoo8_addon_l10n_ar_cash_register-8.0.1.0.0.dist-info/top_level.txt
odoo8_addon_l10n_ar_cash_register-8.0.1.0.0.dist-info/WHEEL
odoo8_addon_l10n_ar_cash_register-8.0.1.0.0.dist-info/RECORD
odoo8_addon_l10n_ar_cash_register-8.0.1.0.0.dist-info/metadata.json
odoo8_addon_l10n_ar_cash_register-8.0.1.0.0.dist-info/DESCRIPTION.rst
odoo8_addon_l10n_ar_cash_register-8.0.1.0.0.dist-info/METADATA
odoo8_addon_l10n_ar_cash_register-8.0.1.0.0.dist-info/namespace_packages.txt
